gear_torque_calc/__init__.py
gear_torque_calc/main.py
gear_torque_calc-1.0.1.dist-info/METADATA
gear_torque_calc-1.0.1.dist-info/WHEEL
gear_torque_calc-1.0.1.dist-info/top_level.txt
gear_torque_calc-1.0.1.dist-info/RECORD
