Metadata-Version: 2.1
Name: gear-torque-calc
Version: 1.0.1
Summary: Get torque output based on gear sizes
Home-page: https://github.com/ncrmro/gear-torque-calc
Author: Nicholas Romero
Author-email: ncrmro@gmail.com
License: MIT
Platform: UNKNOWN
Classifier: Programming Language :: Python :: 3
